fastapi_batch/__init__.py
fastapi_batch/gateway.py
fastapi_batch/py.typed
fastapi_batch/models/__init__.py
fastapi_batch/models/batch_model.py
fastapi_batch/models/batch_request.py
fastapi_batch/models/batch_response.py
fastapi_batch/models/http_methods.py
fastapi_batch-1.0.1.dist-info/METADATA
fastapi_batch-1.0.1.dist-info/WHEEL
fastapi_batch-1.0.1.dist-info/licenses/LICENSE.md
fastapi_batch-1.0.1.dist-info/RECORD
