Metadata-Version: 2.3
Name: fastapi-batch
Version: 1.0.1
Summary: FastAPI dependency for batch requesting
Project-URL: Homepage, https://github.com/sarbagyastha/fastapi-batch
Project-URL: Documentation, https://github.com/sarbagyastha/fastapi-batch/blob/main/README.md
Project-URL: Repository, https://github.com/sarbagyastha/fastapi-batch
Project-URL: Issues, https://github.com/sarbagyastha/fastapi-batch/issues
Project-URL: Changelog, https://github.com/sarbagyastha/fastapi-batch/blob/main/CHANGELOG.md
Author-email: Sarbagya Dhaubanjar <sarbagyastha@gmail.com>
License: MIT
Classifier: Environment :: Web Environment
Classifier: Framework :: AsyncIO
Classifier: Framework :: FastAPI
Classifier: Framework :: Pydantic
Classifier: Framework :: Pydantic :: 1
Classifier: Intended Audience :: Developers
Classifier: Intended Audience :: Information Technology
Classifier: Intended Audience :: System Administrators
Classifier: License :: OSI Approved :: MIT License
Classifier: Operating System :: OS Independent
Classifier: Programming Language :: Python
Classifier: Programming Language :: Python :: 3
Classifier: Programming Language :: Python :: 3 :: Only
Classifier: Programming Language :: Python :: 3.8
Classifier: Programming Language :: Python :: 3.9
Classifier: Programming Language :: Python :: 3.10
Classifier: Programming Language :: Python :: 3.11
Classifier: Programming Language :: Python :: 3.12
Classifier: Programming Language :: Python :: 3.13
Classifier: Topic :: Internet
Classifier: Topic :: Internet :: WWW/HTTP
Classifier: Topic :: Internet :: WWW/HTTP :: HTTP Servers
Classifier: Topic :: Software Development
Classifier: Topic :: Software Development :: Libraries
Classifier: Topic :: Software Development :: Libraries :: Application Frameworks
Classifier: Topic :: Software Development :: Libraries :: Python Modules
Classifier: Typing :: Typed
Requires-Python: >=3.12
Requires-Dist: asyncer>=0.0.8
Requires-Dist: fastapi>=0.115.6
Requires-Dist: httpx>=0.28.1
